README.md
setup.py
logone/__init__.py
logone/logone.py
logone.egg-info/PKG-INFO
logone.egg-info/SOURCES.txt
logone.egg-info/dependency_links.txt
logone.egg-info/not-zip-safe
logone.egg-info/requires.txt
logone.egg-info/top_level.txt