Metadata-Version: 1.0
Name: logone
Version: 0.1.7
Summary: A simple logger which supports for logging stdout and stderr streams to console, file, and Loggly for Python
Home-page: https://github.com/dnanhkhoa/logone
Author: Duong Nguyen Anh Khoa
Author-email: dnanhkhoa@live.com
License: MIT
Keywords: logone logger logging loggly stream log file stdout stderr
Platform: UNKNOWN
